truelearn/__init__.py
truelearn/_constraint.py
truelearn/base.py
truelearn/errors.py
truelearn/datasets/__init__.py
truelearn/datasets/_base.py
truelearn/datasets/_peek.py
truelearn/learning/__init__.py
truelearn/learning/_base.py
truelearn/learning/_engage_classifier.py
truelearn/learning/_ink_classifier.py
truelearn/learning/_interest_classifier.py
truelearn/learning/_knowledge_classifier.py
truelearn/learning/_majority_classifier.py
truelearn/learning/_novelty_classifier.py
truelearn/learning/_persistent_classifier.py
truelearn/models/__init__.py
truelearn/models/_base.py
truelearn/models/_event.py
truelearn/models/_knowledge.py
truelearn/models/_learner.py
truelearn/preprocessing/__init__.py
truelearn/preprocessing/_utils.py
truelearn/preprocessing/_wikifier.py
truelearn/utils/__init__.py
truelearn/utils/metrics/__init__.py
truelearn/utils/metrics/_classification.py
truelearn/utils/visualisations/__init__.py
truelearn/utils/visualisations/_bar_plotter.py
truelearn/utils/visualisations/_base.py
truelearn/utils/visualisations/_bubble_plotter.py
truelearn/utils/visualisations/_dot_plotter.py
truelearn/utils/visualisations/_line_plotter.py
truelearn/utils/visualisations/_pie_rose_plotter.py
truelearn/utils/visualisations/_radar_plotter.py
truelearn/utils/visualisations/_treemap_plotter.py
truelearn/utils/visualisations/_word_plotter.py
truelearn-1.1.0.dist-info/LICENSE
truelearn-1.1.0.dist-info/LICENSE-3RD-PARTY
truelearn-1.1.0.dist-info/METADATA
truelearn-1.1.0.dist-info/WHEEL
truelearn-1.1.0.dist-info/top_level.txt
truelearn-1.1.0.dist-info/RECORD
