Metadata-Version: 2.1
Name: truelearn
Version: 1.1.0
Summary: A Machine learning library that models and predicts learner engagement
Author: Sahanbull, KD-7, yuxqiu, deniselezi, aaneelshalman
License: MIT License
Project-URL: Homepage, https://truelearnai.github.io/
Project-URL: Documentation, https://truelearn.readthedocs.io/en/stable/
Project-URL: Issues, https://github.com/TrueLearnAI/truelearn/issues
Project-URL: Source, https://github.com/TrueLearnAI/truelearn
Keywords: machine learning,python,statistics,probability
Classifier: License :: OSI Approved :: MIT License
Classifier: Intended Audience :: Science/Research
Classifier: Intended Audience :: Developers
Classifier: Intended Audience :: Education
Classifier: Programming Language :: Python :: 3.7
Classifier: Programming Language :: Python :: 3.8
Classifier: Programming Language :: Python :: 3.9
Classifier: Programming Language :: Python :: 3.10
Classifier: Programming Language :: Python :: 3.11
Classifier: Development Status :: 5 - Production/Stable
Classifier: Operating System :: Microsoft :: Windows
Classifier: Operating System :: MacOS
Classifier: Operating System :: Unix
Classifier: Topic :: Scientific/Engineering :: Artificial Intelligence
Classifier: Topic :: Software Development :: Libraries
Classifier: Topic :: Education
Requires-Python: >=3.7
License-File: LICENSE
License-File: LICENSE-3RD-PARTY
Requires-Dist: typing-extensions >=4.7.1
Requires-Dist: trueskill >=0.4.5
Requires-Dist: mpmath >=1.3.0
Requires-Dist: circlify >=0.15.0
Requires-Dist: scikit-learn >=1.0.2
Requires-Dist: matplotlib >=3.5.3
Requires-Dist: plotly ==5.14.1
Requires-Dist: wordcloud ==1.9.2
Requires-Dist: kaleido ==0.2.1 ; sys_platform != "win32"
Requires-Dist: kaleido ==0.1.0.post1 ; sys_platform == "win32"
Provides-Extra: dev
Requires-Dist: truelearn[docs,linters,tests] ; extra == 'dev'
Requires-Dist: black >=22.12.0 ; extra == 'dev'
Provides-Extra: docs
Requires-Dist: sphinx >=5.3.0 ; extra == 'docs'
Requires-Dist: furo >=2023.03.27 ; extra == 'docs'
Requires-Dist: sphinx-copybutton >=0.5.1 ; extra == 'docs'
Requires-Dist: sphinx-gallery >=0.12.2 ; extra == 'docs'
Requires-Dist: Pillow >=9.4.0 ; extra == 'docs'
Provides-Extra: linters
Requires-Dist: prospector[with_bandit,with_mypy] ==1.8.4 ; extra == 'linters'
Provides-Extra: tests
Requires-Dist: pytest >=7.2.1 ; extra == 'tests'
Requires-Dist: pytest-cov >=4.0.0 ; extra == 'tests'
Requires-Dist: pytest-socket >=0.6.0 ; extra == 'tests'
